main.py
arpc/__init__.py
arpc/base/__init__.py
arpc/base/base.py
arpc/client/__init__.py
arpc/client/client.py
arpc/client/client_async.py
arpc/server/__init__.py
arpc/server/server.py
arpc/server/server_async.py
arpc/utils/__init__.py
arpc/utils/arpc.py
arpc/utils/arpc_template.py
arpc/utils/main.py
arpc/utils/metadata.py
arpc/utils/snake_util.py
tests/__init__.py
tests/test_compile.py
arpc-0.1.0.dist-info/LICENSE
arpc-0.1.0.dist-info/METADATA
arpc-0.1.0.dist-info/WHEEL
arpc-0.1.0.dist-info/entry_points.txt
arpc-0.1.0.dist-info/top_level.txt
arpc-0.1.0.dist-info/RECORD
