Metadata-Version: 2.1
Name: arpc
Version: 0.1.0
Summary: A framework of remote procedure call.
Home-page: https://github.com/ahrirpc/arpc-python
Author: ahriknow
Author-email: ahriknow@ahriknow.com
License: Apache License 2.0
Platform: any
Classifier: Programming Language :: Python :: 3
Classifier: License :: OSI Approved :: Apache Software License
Classifier: Operating System :: OS Independent
Requires-Python: >=3.6
License-File: LICENSE
Provides-Extra: async
Requires-Dist: nest-asyncio (>=1.5.6) ; extra == 'async'
